flask_jsonapi_trivial/__init__.py
flask_jsonapi_trivial-0.2.5.dist-info/LICENSE
flask_jsonapi_trivial-0.2.5.dist-info/METADATA
flask_jsonapi_trivial-0.2.5.dist-info/WHEEL
flask_jsonapi_trivial-0.2.5.dist-info/top_level.txt
flask_jsonapi_trivial-0.2.5.dist-info/RECORD
