Metadata-Version: 2.1
Name: flask-jsonapi-trivial
Version: 0.2.5
Summary: Provides Flask with *very basic* JSONAPI.org compliance
Home-page: http://github.com/subsect/flask_jsonapi_trivial/
Author: austinjp
Author-email: austin.plunkett+pypi@gmail.com
License: CC BY-NC-SA 4.0
Platform: any
Classifier: Development Status :: 3 - Alpha
Classifier: Environment :: Web Environment
Classifier: Framework :: Flask
Classifier: Intended Audience :: Developers
Classifier: License :: Free for non-commercial use
Classifier: Operating System :: OS Independent
Classifier: Programming Language :: Python :: 3
Classifier: Topic :: Internet :: WWW/HTTP :: WSGI
Classifier: Topic :: Software Development :: Libraries :: Application Frameworks
Classifier: Topic :: Software Development :: Libraries :: Python Modules
Requires-Python: ~=3.6
Requires-Dist: cryptography (>=2.9.2)
Requires-Dist: Flask (>=1.0.2)
Requires-Dist: python-jose[cryptography] (>=3.1.0)
Requires-Dist: Werkzeug (>=0.15.3)
